gazel/Tracker.py
gazel/__init__.py
gazel/common.py
gazel/core.py
gazel/core_types.py
gazel/parsing.py
gazel/pprint.py
gazel/test_tracker.py
gazel/fixation_filters/__init__.py
gazel/fixation_filters/basic.py
gazel/fixation_filters/core.py
gazel/fixation_filters/fixation_data.py
gazel/fixation_filters/idt.py
gazel/fixation_filters/ivt.py
src/Tracker.py
src/__init__.py
src/common.py
src/core.py
src/core_types.py
src/parsing.py
src/test_tracker.py
src/fixation_filters/__init__.py
src/fixation_filters/basic.py
src/fixation_filters/core.py
src/fixation_filters/fixation_data.py
src/fixation_filters/idt.py
src/fixation_filters/ivt.py
gazel-0.0.7.dist-info/LICENSE
gazel-0.0.7.dist-info/METADATA
gazel-0.0.7.dist-info/WHEEL
gazel-0.0.7.dist-info/top_level.txt
gazel-0.0.7.dist-info/RECORD
