Metadata-Version: 2.1
Name: gazel
Version: 0.0.7
Summary: Track fixations across edits for eyetracking experiments
Home-page: https://github.com/devjeetrr/pytrace
Author: Devjeet Roy
Author-email: devjeetrr@gmail.com
License: UNKNOWN
Platform: UNKNOWN
Classifier: Programming Language :: Python :: 3
Classifier: License :: OSI Approved :: MIT License
Classifier: Operating System :: OS Independent
Requires-Python: >=3.8.5
